abfml/__init__.py
abfml/calculate.py
abfml/lmp.py
abfml/main.py
abfml/core/__init__.py
abfml/core/loss/__init__.py
abfml/core/loss/losser.py
abfml/core/model/__init__.py
abfml/core/model/bpmlp.py
abfml/core/model/dpse.py
abfml/core/model/math_fun.py
abfml/core/model/method.py
abfml/core/model/nep.py
abfml/core/model/network.py
abfml/core/model/normal.py
abfml/core/optimizer/__init__.py
abfml/core/optimizer/learn_rate.py
abfml/core/optimizer/optim_init.py
abfml/data/__init__.py
abfml/data/dataset.py
abfml/data/read_data.py
abfml/entrypoints/__init__.py
abfml/entrypoints/check.py
abfml/entrypoints/main_command.py
abfml/entrypoints/main_parser.py
abfml/entrypoints/train.py
abfml/entrypoints/valid.py
abfml/logger/__init__.py
abfml/logger/loggers.py
abfml/param/__init__.py
abfml/param/param.py
abfml/train/__init__.py
abfml/train/trainer.py
abfml/utils/chart.py
abfml-2025.5.8.dist-info/licenses/LICENSE
abfml-2025.5.8.dist-info/METADATA
abfml-2025.5.8.dist-info/WHEEL
abfml-2025.5.8.dist-info/entry_points.txt
abfml-2025.5.8.dist-info/top_level.txt
abfml-2025.5.8.dist-info/RECORD
