Metadata-Version: 2.4
Name: abfml
Version: 2025.5.8
Summary: A problem-oriented package for rapidly creating, screening, and optimizing new machine learning force fields
Author-email: GengXingZe <1308186024@qq.com>
License-Expression: GPL-3.0-only
Project-URL: Homepage, https://github.com/gengxingze/ABFML/
Project-URL: Repository, https://github.com/gengxingze/ABFML/
Keywords: machine learning,force fields,LAMMPS,MLFF,abfml
Requires-Python: >=3.11
License-File: LICENSE
Requires-Dist: ase==3.22.0
Requires-Dist: numpy==1.25.0
Requires-Dist: matplotlib==3.9.2
Requires-Dist: torch>=2.2.1
Requires-Dist: jsonschema==4.23.0
Dynamic: license-file
